{
  "run": {
    "command": "nx build web",
    "startTime": "2025-09-01T20:32:20.696Z",
    "endTime": "2025-09-01T20:32:20.718Z",
    "inner": false
  },
  "tasks": [
    {
      "taskId": "utils:build",
      "target": "build",
      "projectName": "utils",
      "hash": "3387989889015470484",
      "startTime": "2025-09-01T20:32:20.699Z",
      "endTime": "2025-09-01T20:32:20.715Z",
      "params": "",
      "cacheStatus": "local-cache-hit",
      "status": 0
    },
    {
      "taskId": "web:build",
      "target": "build",
      "projectName": "web",
      "hash": "17974615291287238416",
      "startTime": "2025-09-01T20:32:20.716Z",
      "endTime": "2025-09-01T20:32:20.717Z",
      "params": "",
      "cacheStatus": "local-cache-hit",
      "status": 0
    }
  ]
}
